inoutlists/EU_20171012-FULL-schema-1_1(xsd).xsd
inoutlists/OFAC_Id_Types.csv
inoutlists/OFAC_xml.xsd
inoutlists/UN_consolidated.xsd
inoutlists/__init__.py
inoutlists/country_ISO_codes.csv
inoutlists/country_names.csv
inoutlists/dumpers.py
inoutlists/loaders.py
inoutlists-1.0.1.dist-info/METADATA
inoutlists-1.0.1.dist-info/WHEEL
inoutlists-1.0.1.dist-info/licenses/LICENSE
inoutlists-1.0.1.dist-info/RECORD
