Metadata-Version: 2.3
Name: inoutlists
Version: 1.0.1
Summary: inoutlists is a python package to parse and normalize different sources of lists (OFAC, EU, UN, etc) to a common dictionary interface.
Project-URL: Homepage, https://github.com/ejtorre/inoutlists
Project-URL: Documentation, https://ejtorre.github.io/inoutlists/
Project-URL: Repository, https://github.com/ejtorre/inoutlists
Project-URL: Source, https://github.com/ejtorre/inoutlists
Author-email: Eusebio José de la Torre Niño <ej.torre.nino@gmail.com>
Maintainer-email: Eusebio José de la Torre Niño <ej.torre.nino@gmail.com>
License: MIT License
License-File: LICENSE
Keywords: EU,OFAC,UN,decoding,deduplication,encoding,entity-resolution,lists,mapping,normalization,parsing,record-linkage,sanctions
Classifier: Development Status :: 5 - Production/Stable
Classifier: Environment :: Console
Classifier: Intended Audience :: Developers
Classifier: Intended Audience :: Science/Research
Classifier: License :: OSI Approved :: MIT License
Classifier: Operating System :: OS Independent
Classifier: Programming Language :: Python :: 3
Requires-Python: >=3.8
Requires-Dist: lxml>=5.2.2
Requires-Dist: pandas>=2.2.2
Requires-Dist: requests>=2.32.2
